BeginnersbookPerlJiaochengChuyi/README.md
BeginnersbookPerlJiaochengChuyi/__init__.py
BeginnersbookPerlJiaochengChuyi/__main__.py
BeginnersbookPerlJiaochengChuyi/file.epub
BeginnersbookPerlJiaochengChuyi/index.html
BeginnersbookPerlJiaochengChuyi/css/__init__.py
BeginnersbookPerlJiaochengChuyi/css/annotations.css
BeginnersbookPerlJiaochengChuyi/css/main.css
BeginnersbookPerlJiaochengChuyi/css/normalize.css
BeginnersbookPerlJiaochengChuyi/css/popup.css
BeginnersbookPerlJiaochengChuyi/font/__init__.py
BeginnersbookPerlJiaochengChuyi/font/fontello.eot
BeginnersbookPerlJiaochengChuyi/font/fontello.svg
BeginnersbookPerlJiaochengChuyi/font/fontello.ttf
BeginnersbookPerlJiaochengChuyi/font/fontello.woff
BeginnersbookPerlJiaochengChuyi/img/__init__.py
BeginnersbookPerlJiaochengChuyi/img/annotator-glyph-sprite.png
BeginnersbookPerlJiaochengChuyi/img/annotator-icon-sprite.png
BeginnersbookPerlJiaochengChuyi/img/apple-touch-icon.png
BeginnersbookPerlJiaochengChuyi/img/cancelfullscreen.png
BeginnersbookPerlJiaochengChuyi/img/close.png
BeginnersbookPerlJiaochengChuyi/img/fullscreen.png
BeginnersbookPerlJiaochengChuyi/img/loader.gif
BeginnersbookPerlJiaochengChuyi/img/menu-icon.png
BeginnersbookPerlJiaochengChuyi/img/save.png
BeginnersbookPerlJiaochengChuyi/img/saved.png
BeginnersbookPerlJiaochengChuyi/img/settings-s.png
BeginnersbookPerlJiaochengChuyi/img/settings.png
BeginnersbookPerlJiaochengChuyi/img/star.png
BeginnersbookPerlJiaochengChuyi/js/__init__.py
BeginnersbookPerlJiaochengChuyi/js/epub.js
BeginnersbookPerlJiaochengChuyi/js/epub.min.js
BeginnersbookPerlJiaochengChuyi/js/epub.min.map
BeginnersbookPerlJiaochengChuyi/js/hooks.min.js
BeginnersbookPerlJiaochengChuyi/js/hooks.min.map
BeginnersbookPerlJiaochengChuyi/js/reader.js
BeginnersbookPerlJiaochengChuyi/js/reader.js.map
BeginnersbookPerlJiaochengChuyi/js/reader.min.js
BeginnersbookPerlJiaochengChuyi/js/reader.min.map
BeginnersbookPerlJiaochengChuyi/js/hooks/__init__.py
beginnersbook_perl_jiaocheng_chuyi-2024.3.5.0.dist-info/METADATA
beginnersbook_perl_jiaocheng_chuyi-2024.3.5.0.dist-info/WHEEL
beginnersbook_perl_jiaocheng_chuyi-2024.3.5.0.dist-info/entry_points.txt
beginnersbook_perl_jiaocheng_chuyi-2024.3.5.0.dist-info/top_level.txt
beginnersbook_perl_jiaocheng_chuyi-2024.3.5.0.dist-info/RECORD
